grammlog/__init__.py
grammlog/py.typed
grammlog-1.4.1.dist-info/METADATA
grammlog-1.4.1.dist-info/WHEEL
grammlog-1.4.1.dist-info/licenses/LICENSE
grammlog-1.4.1.dist-info/RECORD
