Metadata-Version: 2.3
Name: grammlog
Version: 1.4.1
Summary: Structured logging to JSONL with support for asynchronous logging via asyncio
Project-URL: homepage, https://github.com/GrammAcc/grammlog
Project-URL: bug_tracker, https://github.com/GrammAcc/grammlog/issues
Project-URL: documentation, https://grammacc.github.io/grammlog
Project-URL: repository, https://github.com/GrammAcc/grammlog
Author: GrammAcc
Maintainer: GrammAcc
License: MIT
Keywords: asyncio,json-logging,logging,structured-logging
Classifier: Development Status :: 5 - Production/Stable
Classifier: Framework :: AsyncIO
Classifier: Intended Audience :: Developers
Classifier: Intended Audience :: System Administrators
Classifier: Operating System :: OS Independent
Classifier: Programming Language :: Python :: 3
Classifier: Topic :: File Formats :: JSON
Classifier: Topic :: System :: Logging
Classifier: Topic :: Utilities
Classifier: Typing :: Typed
Requires-Python: >=3.10
Provides-Extra: dev
Requires-Dist: hatch; extra == 'dev'
